{"hand": "340999s66p406777m", "melds": [], "openHand": false, "winningTile": "0m", "riichiSticks": 4, "honbaSticks": 2, "roundWind": "SOUTH", "seatWind": "2h", "doraIndicators": ["2h"], "uraDoraIndicators": ["6m"], "isDealer": false, "isTsumo": false, "isRiichi": true, "yakusAchieved": {"1": 1, "54": 2, "53": 3}, "pointValue": "12000", "fu": "50", "han": 6, "fu_details": [{"fu": 30, "reason": "base"}, {"fu": 8, "reason": "closed_terminal_pon"}, {"fu": 4, "reason": "closed_pon"}, {"fu": 2, "reason": "kanchan"}, {"fu": 6, "reason": "rounding"}]}