{"hand": "22s345p", "melds": ["8c88m", "c345m", "7c77h"], "openHand": true, "winningTile": "3p", "riichiSticks": 0, "honbaSticks": 0, "roundWind": "EAST", "seatWind": "3h", "doraIndicators": ["6m"], "uraDoraIndicators": [], "isDealer": false, "isTsumo": false, "isRiichi": false, "yakusAchieved": {"20": 1}, "pointValue": "1000", "fu": "30", "han": 1, "fu_details": [{"fu": 20, "reason": "base"}, {"fu": 4, "reason": "open_terminal_pon"}, {"fu": 2, "reason": "open_pon"}, {"fu": 4, "reason": "rounding"}]}