{"hand": "345s11m", "melds": ["4c44m", "7c77m", "c222h"], "openHand": true, "winningTile": "5s", "riichiSticks": 0, "honbaSticks": 2, "roundWind": "EAST", "seatWind": "2h", "doraIndicators": ["2m"], "uraDoraIndicators": [], "isDealer": false, "isTsumo": false, "isRiichi": false, "yakusAchieved": {"11": 1}, "pointValue": "1000", "fu": "30", "han": 1, "fu_details": [{"fu": 20, "reason": "base"}, {"fu": 4, "reason": "open_terminal_pon"}, {"fu": 2, "reason": "open_pon"}, {"fu": 2, "reason": "open_pon"}, {"fu": 2, "reason": "rounding"}]}