{"hand": "33067789s406p", "melds": ["c555h"], "openHand": true, "winningTile": "7s", "riichiSticks": 0, "honbaSticks": 0, "roundWind": "SOUTH", "seatWind": "1h", "doraIndicators": ["3m"], "uraDoraIndicators": [], "isDealer": true, "isTsumo": false, "isRiichi": false, "yakusAchieved": {"18": 1, "54": 2}, "pointValue": "5800", "fu": "30", "han": 3, "fu_details": [{"fu": 20, "reason": "base"}, {"fu": 4, "reason": "open_terminal_pon"}, {"fu": 2, "reason": "penchan"}, {"fu": 4, "reason": "rounding"}]}